pytenable-1.8.4.dist-info/licenses/LICENSE
tenable/__init__.py
tenable/constants.py
tenable/errors.py
tenable/utils.py
tenable/version.py
tenable/vm.py
tenable/apa/__init__.py
tenable/apa/findings/__init__.py
tenable/apa/findings/api.py
tenable/apa/findings/schema.py
tenable/apa/vectors/__init__.py
tenable/apa/vectors/api.py
tenable/apa/vectors/schema.py
tenable/asm/__init__.py
tenable/asm/inventory.py
tenable/asm/session.py
tenable/asm/smart_folders.py
tenable/base/__init__.py
tenable/base/endpoint.py
tenable/base/graphql.py
tenable/base/platform.py
tenable/base/v1.py
tenable/base/schema/__init__.py
tenable/base/schema/fields.py
tenable/base/utils/__init__.py
tenable/base/utils/envelope.py
tenable/cloudsecurity/__init__.py
tenable/cloudsecurity/assets.py
tenable/cloudsecurity/session.py
tenable/cloudsecurity/vulns.py
tenable/cloudsecurity/queries/assets-compute.graphql
tenable/cloudsecurity/queries/assets-container.graphql
tenable/cloudsecurity/queries/vulns-containerimage.graphql
tenable/cloudsecurity/queries/vulns-virtualmachine.graphql
tenable/dl/__init__.py
tenable/ie/__init__.py
tenable/ie/about.py
tenable/ie/api_keys.py
tenable/ie/session.py
tenable/ie/ad_object/__init__.py
tenable/ie/ad_object/api.py
tenable/ie/ad_object/schema.py
tenable/ie/alert/__init__.py
tenable/ie/alert/api.py
tenable/ie/alert/schema.py
tenable/ie/application_settings/__init__.py
tenable/ie/application_settings/api.py
tenable/ie/application_settings/schema.py
tenable/ie/attack_type_options/__init__.py
tenable/ie/attack_type_options/api.py
tenable/ie/attack_type_options/schema.py
tenable/ie/attack_types/__init__.py
tenable/ie/attack_types/api.py
tenable/ie/attack_types/schema.py
tenable/ie/attacks/__init__.py
tenable/ie/attacks/api.py
tenable/ie/attacks/schema.py
tenable/ie/base/__init__.py
tenable/ie/base/iterator.py
tenable/ie/base/schema.py
tenable/ie/category/__init__.py
tenable/ie/category/api.py
tenable/ie/category/schema.py
tenable/ie/checker/__init__.py
tenable/ie/checker/api.py
tenable/ie/checker/schema.py
pytenable-1.8.4.dist-info/METADATA
pytenable-1.8.4.dist-info/WHEEL
pytenable-1.8.4.dist-info/top_level.txt
pytenable-1.8.4.dist-info/RECORD
